spotify_data_analytics/__init__.py
spotify_data_analytics/cli.py
spotify_data_analytics/extract_data.py
spotify_data_analytics/load_data.py
spotify_data_analytics/transform_data.py
spotify_data_analytics/utils.py
spotify_data_analytics-0.1.0.dist-info/licenses/LICENSE
spotify_data_analytics-0.1.0.dist-info/METADATA
spotify_data_analytics-0.1.0.dist-info/WHEEL
spotify_data_analytics-0.1.0.dist-info/entry_points.txt
spotify_data_analytics-0.1.0.dist-info/top_level.txt
spotify_data_analytics-0.1.0.dist-info/RECORD
