Metadata-Version: 2.4
Name: spotify-data-analytics
Version: 0.1.0
Summary: End-to-end Spotify data analytics pipeline (ETL + analysis)
Author: Lingeswaran R
Keywords: spotify,etl,analytics,data-engineering
Classifier: Programming Language :: Python :: 3
Classifier: License :: OSI Approved :: MIT License
Requires-Python: >=3.8
License-File: LICENSE
Requires-Dist: pandas>=2.2.2
Requires-Dist: numpy>=1.26.4
Requires-Dist: spotipy>=2.23.0
Requires-Dist: python-dotenv>=1.0.1
Requires-Dist: matplotlib>=3.8.4
Requires-Dist: scikit-learn>=1.4.2
Requires-Dist: pyarrow>=16.1.0
Dynamic: license-file
